{"index":{"links":{"/":[{"source":"/","target":"/notes/Asphodelos","text":"Asphodelos"},{"source":"/","target":"/notes/P1S-Ericthonios","text":"P1S - Ericthonios"},{"source":"/","target":"/notes/P2S-Hippokampos","text":"P2S - Hippokampos"},{"source":"/","target":"/notes/P3S-Phoinix","text":"P3S - Phoinix"},{"source":"/","target":"/notes/P4S-Hesperos","text":"P4S - Hesperos"},{"source":"/","target":"/notes/Ultimate","text":"Ultimate"},{"source":"/","target":"/Ultima-Weapon-Ultimate","text":"Ultima Weapon Ultimate"},{"source":"/","target":"/Ultimate-Coils-of-Bahamut","text":"Ultimate Coils of Bahamut"},{"source":"/","target":"/The-Epic-of-Alexander-Ultimate","text":"The Epic of Alexander Ultimate"},{"source":"/","target":"/notes/Dragonsong-War-Ultimate","text":"Dragonsong War Ultimate"},{"source":"/","target":"/notes/Tank-Resources","text":"Tank Resources"},{"source":"/","target":"/notes/Healer-Resources","text":"Healer Resources"},{"source":"/","target":"/notes/Melee-Resources","text":"Melee Resources"},{"source":"/","target":"/notes/Caster-Resources","text":"Caster Resources"},{"source":"/","target":"/notes/Ranged-Resources","text":"Ranged Resources"}],"/notes/Asphodelos":[{"source":"/notes/Asphodelos","target":"/notes/P1S-Ericthonios","text":"P1S - Ericthonios"},{"source":"/notes/Asphodelos","target":"/notes/P2S-Hippokampos","text":"P2S - Hippokampos"},{"source":"/notes/Asphodelos","target":"/notes/P3S-Phoinix","text":"P3S - Phoinix"},{"source":"/notes/Asphodelos","target":"/notes/P4S-Hesperos","text":"P4S - Hesperos"}],"/notes/Caster-Resources":[{"source":"/notes/Caster-Resources","target":"/_index","text":"Back"},{"source":"/notes/Caster-Resources","target":"/notes/Summoner","text":"Summoner"},{"source":"/notes/Caster-Resources","target":"/notes/Black-Mage","text":"Black Mage"},{"source":"/notes/Caster-Resources","target":"/notes/Red-Mage","text":"Red Mage"}],"/notes/Dragonsong-War-Ultimate":[{"source":"/notes/Dragonsong-War-Ultimate","target":"/notes/Ultimate","text":"Back"}],"/notes/Healer-Resources":[{"source":"/notes/Healer-Resources","target":"/_index","text":"Back"},{"source":"/notes/Healer-Resources","target":"/notes/Sage","text":"Sage"},{"source":"/notes/Healer-Resources","target":"/notes/Scholar","text":"Scholar"},{"source":"/notes/Healer-Resources","target":"/notes/Astrologian","text":"Astrologian"},{"source":"/notes/Healer-Resources","target":"/notes/White-Mage","text":"White Mage"}],"/notes/Melee-Resources":[{"source":"/notes/Melee-Resources","target":"/_index","text":"Back"},{"source":"/notes/Melee-Resources","target":"/notes/Reaper","text":"Reaper"},{"source":"/notes/Melee-Resources","target":"/notes/Monk","text":"Monk"},{"source":"/notes/Melee-Resources","target":"/notes/Dragoon","text":"Dragoon"},{"source":"/notes/Melee-Resources","target":"/notes/Ninja","text":"Ninja"},{"source":"/notes/Melee-Resources","target":"/notes/Samurai","text":"Samurai"}],"/notes/P1S-Ericthonios":[{"source":"/notes/P1S-Ericthonios","target":"/notes/Asphodelos","text":"Back"}],"/notes/P2S-Hippokampos":[{"source":"/notes/P2S-Hippokampos","target":"/notes/Asphodelos","text":"Back"}],"/notes/P3S-Phoinix":[{"source":"/notes/P3S-Phoinix","target":"/notes/Asphodelos","text":"Back"}],"/notes/P4S-Hesperos":[{"source":"/notes/P4S-Hesperos","target":"/notes/Asphodelos","text":"Back"}],"/notes/Ranged-Resources":[{"source":"/notes/Ranged-Resources","target":"/_index","text":"Back"},{"source":"/notes/Ranged-Resources","target":"/notes/Dancer","text":"Dancer"},{"source":"/notes/Ranged-Resources","target":"/notes/Bard","text":"Bard"},{"source":"/notes/Ranged-Resources","target":"/notes/Machinist","text":"Machinist"}],"/notes/Tank-Resources":[{"source":"/notes/Tank-Resources","target":"/_index","text":"Back"},{"source":"/notes/Tank-Resources","target":"/Dark-Knight","text":"Dark Knight"},{"source":"/notes/Tank-Resources","target":"/Gunbreaker","text":"Gunbreaker"},{"source":"/notes/Tank-Resources","target":"/notes/Paladin","text":"Paladin"},{"source":"/notes/Tank-Resources","target":"/notes/Warrior","text":"Warrior"}],"/notes/Ultimate":[{"source":"/notes/Ultimate","target":"/Ultima-Weapon-Ultimate","text":"Ultima Weapon Ultimate"},{"source":"/notes/Ultimate","target":"/Ultimate-Coils-of-Bahamut","text":"Ultimate Coils of Bahamut"},{"source":"/notes/Ultimate","target":"/The-Epic-of-Alexander-Ultimate","text":"The Epic of Alexander Ultimate"},{"source":"/notes/Ultimate","target":"/notes/Dragonsong-War-Ultimate","text":"Dragonsong War Ultimate"}]},"backlinks":{"/Dark-Knight":[{"source":"/notes/Tank-Resources","target":"/Dark-Knight","text":"Dark Knight"}],"/Gunbreaker":[{"source":"/notes/Tank-Resources","target":"/Gunbreaker","text":"Gunbreaker"}],"/The-Epic-of-Alexander-Ultimate":[{"source":"/","target":"/The-Epic-of-Alexander-Ultimate","text":"The Epic of Alexander Ultimate"},{"source":"/notes/Ultimate","target":"/The-Epic-of-Alexander-Ultimate","text":"The Epic of Alexander Ultimate"}],"/Ultima-Weapon-Ultimate":[{"source":"/","target":"/Ultima-Weapon-Ultimate","text":"Ultima Weapon Ultimate"},{"source":"/notes/Ultimate","target":"/Ultima-Weapon-Ultimate","text":"Ultima Weapon Ultimate"}],"/Ultimate-Coils-of-Bahamut":[{"source":"/","target":"/Ultimate-Coils-of-Bahamut","text":"Ultimate Coils of Bahamut"},{"source":"/notes/Ultimate","target":"/Ultimate-Coils-of-Bahamut","text":"Ultimate Coils of Bahamut"}],"/_index":[{"source":"/notes/Caster-Resources","target":"/_index","text":"Back"},{"source":"/notes/Healer-Resources","target":"/_index","text":"Back"},{"source":"/notes/Melee-Resources","target":"/_index","text":"Back"},{"source":"/notes/Ranged-Resources","target":"/_index","text":"Back"},{"source":"/notes/Tank-Resources","target":"/_index","text":"Back"}],"/notes/Asphodelos":[{"source":"/","target":"/notes/Asphodelos","text":"Asphodelos"},{"source":"/notes/P1S-Ericthonios","target":"/notes/Asphodelos","text":"Back"},{"source":"/notes/P2S-Hippokampos","target":"/notes/Asphodelos","text":"Back"},{"source":"/notes/P3S-Phoinix","target":"/notes/Asphodelos","text":"Back"},{"source":"/notes/P4S-Hesperos","target":"/notes/Asphodelos","text":"Back"}],"/notes/Astrologian":[{"source":"/notes/Healer-Resources","target":"/notes/Astrologian","text":"Astrologian"}],"/notes/Bard":[{"source":"/notes/Ranged-Resources","target":"/notes/Bard","text":"Bard"}],"/notes/Black-Mage":[{"source":"/notes/Caster-Resources","target":"/notes/Black-Mage","text":"Black Mage"}],"/notes/Caster-Resources":[{"source":"/","target":"/notes/Caster-Resources","text":"Caster Resources"}],"/notes/Dancer":[{"source":"/notes/Ranged-Resources","target":"/notes/Dancer","text":"Dancer"}],"/notes/Dragonsong-War-Ultimate":[{"source":"/","target":"/notes/Dragonsong-War-Ultimate","text":"Dragonsong War Ultimate"},{"source":"/notes/Ultimate","target":"/notes/Dragonsong-War-Ultimate","text":"Dragonsong War Ultimate"}],"/notes/Dragoon":[{"source":"/notes/Melee-Resources","target":"/notes/Dragoon","text":"Dragoon"}],"/notes/Healer-Resources":[{"source":"/","target":"/notes/Healer-Resources","text":"Healer Resources"}],"/notes/Machinist":[{"source":"/notes/Ranged-Resources","target":"/notes/Machinist","text":"Machinist"}],"/notes/Melee-Resources":[{"source":"/","target":"/notes/Melee-Resources","text":"Melee Resources"}],"/notes/Monk":[{"source":"/notes/Melee-Resources","target":"/notes/Monk","text":"Monk"}],"/notes/Ninja":[{"source":"/notes/Melee-Resources","target":"/notes/Ninja","text":"Ninja"}],"/notes/P1S-Ericthonios":[{"source":"/","target":"/notes/P1S-Ericthonios","text":"P1S - Ericthonios"},{"source":"/notes/Asphodelos","target":"/notes/P1S-Ericthonios","text":"P1S - Ericthonios"}],"/notes/P2S-Hippokampos":[{"source":"/","target":"/notes/P2S-Hippokampos","text":"P2S - Hippokampos"},{"source":"/notes/Asphodelos","target":"/notes/P2S-Hippokampos","text":"P2S - Hippokampos"}],"/notes/P3S-Phoinix":[{"source":"/","target":"/notes/P3S-Phoinix","text":"P3S - Phoinix"},{"source":"/notes/Asphodelos","target":"/notes/P3S-Phoinix","text":"P3S - Phoinix"}],"/notes/P4S-Hesperos":[{"source":"/","target":"/notes/P4S-Hesperos","text":"P4S - Hesperos"},{"source":"/notes/Asphodelos","target":"/notes/P4S-Hesperos","text":"P4S - Hesperos"}],"/notes/Paladin":[{"source":"/notes/Tank-Resources","target":"/notes/Paladin","text":"Paladin"}],"/notes/Ranged-Resources":[{"source":"/","target":"/notes/Ranged-Resources","text":"Ranged Resources"}],"/notes/Reaper":[{"source":"/notes/Melee-Resources","target":"/notes/Reaper","text":"Reaper"}],"/notes/Red-Mage":[{"source":"/notes/Caster-Resources","target":"/notes/Red-Mage","text":"Red Mage"}],"/notes/Sage":[{"source":"/notes/Healer-Resources","target":"/notes/Sage","text":"Sage"}],"/notes/Samurai":[{"source":"/notes/Melee-Resources","target":"/notes/Samurai","text":"Samurai"}],"/notes/Scholar":[{"source":"/notes/Healer-Resources","target":"/notes/Scholar","text":"Scholar"}],"/notes/Summoner":[{"source":"/notes/Caster-Resources","target":"/notes/Summoner","text":"Summoner"}],"/notes/Tank-Resources":[{"source":"/","target":"/notes/Tank-Resources","text":"Tank Resources"}],"/notes/Ultimate":[{"source":"/","target":"/notes/Ultimate","text":"Ultimate"},{"source":"/notes/Dragonsong-War-Ultimate","target":"/notes/Ultimate","text":"Back"}],"/notes/Warrior":[{"source":"/notes/Tank-Resources","target":"/notes/Warrior","text":"Warrior"}],"/notes/White-Mage":[{"source":"/notes/Healer-Resources","target":"/notes/White-Mage","text":"White Mage"}]}},"links":[{"source":"/","target":"/notes/Asphodelos","text":"Asphodelos"},{"source":"/","target":"/notes/P1S-Ericthonios","text":"P1S - Ericthonios"},{"source":"/","target":"/notes/P2S-Hippokampos","text":"P2S - Hippokampos"},{"source":"/","target":"/notes/P3S-Phoinix","text":"P3S - Phoinix"},{"source":"/","target":"/notes/P4S-Hesperos","text":"P4S - Hesperos"},{"source":"/","target":"/notes/Ultimate","text":"Ultimate"},{"source":"/","target":"/Ultima-Weapon-Ultimate","text":"Ultima Weapon Ultimate"},{"source":"/","target":"/Ultimate-Coils-of-Bahamut","text":"Ultimate Coils of Bahamut"},{"source":"/","target":"/The-Epic-of-Alexander-Ultimate","text":"The Epic of Alexander Ultimate"},{"source":"/","target":"/notes/Dragonsong-War-Ultimate","text":"Dragonsong War Ultimate"},{"source":"/","target":"/notes/Tank-Resources","text":"Tank Resources"},{"source":"/","target":"/notes/Healer-Resources","text":"Healer Resources"},{"source":"/","target":"/notes/Melee-Resources","text":"Melee Resources"},{"source":"/","target":"/notes/Caster-Resources","text":"Caster Resources"},{"source":"/","target":"/notes/Ranged-Resources","text":"Ranged Resources"},{"source":"/notes/Asphodelos","target":"/notes/P1S-Ericthonios","text":"P1S - Ericthonios"},{"source":"/notes/Asphodelos","target":"/notes/P2S-Hippokampos","text":"P2S - Hippokampos"},{"source":"/notes/Asphodelos","target":"/notes/P3S-Phoinix","text":"P3S - Phoinix"},{"source":"/notes/Asphodelos","target":"/notes/P4S-Hesperos","text":"P4S - Hesperos"},{"source":"/notes/Caster-Resources","target":"/_index","text":"Back"},{"source":"/notes/Caster-Resources","target":"/notes/Summoner","text":"Summoner"},{"source":"/notes/Caster-Resources","target":"/notes/Black-Mage","text":"Black Mage"},{"source":"/notes/Caster-Resources","target":"/notes/Red-Mage","text":"Red Mage"},{"source":"/notes/Dragonsong-War-Ultimate","target":"/notes/Ultimate","text":"Back"},{"source":"/notes/Healer-Resources","target":"/_index","text":"Back"},{"source":"/notes/Healer-Resources","target":"/notes/Sage","text":"Sage"},{"source":"/notes/Healer-Resources","target":"/notes/Scholar","text":"Scholar"},{"source":"/notes/Healer-Resources","target":"/notes/Astrologian","text":"Astrologian"},{"source":"/notes/Healer-Resources","target":"/notes/White-Mage","text":"White Mage"},{"source":"/notes/Melee-Resources","target":"/_index","text":"Back"},{"source":"/notes/Melee-Resources","target":"/notes/Reaper","text":"Reaper"},{"source":"/notes/Melee-Resources","target":"/notes/Monk","text":"Monk"},{"source":"/notes/Melee-Resources","target":"/notes/Dragoon","text":"Dragoon"},{"source":"/notes/Melee-Resources","target":"/notes/Ninja","text":"Ninja"},{"source":"/notes/Melee-Resources","target":"/notes/Samurai","text":"Samurai"},{"source":"/notes/P1S-Ericthonios","target":"/notes/Asphodelos","text":"Back"},{"source":"/notes/P2S-Hippokampos","target":"/notes/Asphodelos","text":"Back"},{"source":"/notes/P3S-Phoinix","target":"/notes/Asphodelos","text":"Back"},{"source":"/notes/P4S-Hesperos","target":"/notes/Asphodelos","text":"Back"},{"source":"/notes/Ranged-Resources","target":"/_index","text":"Back"},{"source":"/notes/Ranged-Resources","target":"/notes/Dancer","text":"Dancer"},{"source":"/notes/Ranged-Resources","target":"/notes/Bard","text":"Bard"},{"source":"/notes/Ranged-Resources","target":"/notes/Machinist","text":"Machinist"},{"source":"/notes/Tank-Resources","target":"/_index","text":"Back"},{"source":"/notes/Tank-Resources","target":"/Dark-Knight","text":"Dark Knight"},{"source":"/notes/Tank-Resources","target":"/Gunbreaker","text":"Gunbreaker"},{"source":"/notes/Tank-Resources","target":"/notes/Paladin","text":"Paladin"},{"source":"/notes/Tank-Resources","target":"/notes/Warrior","text":"Warrior"},{"source":"/notes/Ultimate","target":"/Ultima-Weapon-Ultimate","text":"Ultima Weapon Ultimate"},{"source":"/notes/Ultimate","target":"/Ultimate-Coils-of-Bahamut","text":"Ultimate Coils of Bahamut"},{"source":"/notes/Ultimate","target":"/The-Epic-of-Alexander-Ultimate","text":"The Epic of Alexander Ultimate"},{"source":"/notes/Ultimate","target":"/notes/Dragonsong-War-Ultimate","text":"Dragonsong War Ultimate"}]}